{"segments": [{"start": 0.031, "end": 5.687, "text": " Imagina estar soltero toda tu vida y luego tu familia te obliga a casarte después de morir.", "words": [{"word": "Imagina", "start": 0.031, "end": 0.695, "score": 0.906}, {"word": "estar", "start": 0.736, "end": 0.957, "score": 0.687}, {"word": "soltero", "start": 0.997, "end": 1.38, "score": 0.835}, {"word": "toda", "start": 1.48, "end": 1.641, "score": 0.783}, {"word": "tu", "start": 1.722, "end": 1.822, "score": 0.734}, {"word": "vida", "start": 1.843, "end": 2.064, "score": 0.978}, {"word": "y", "start": 2.084, "end": 2.104, "score": 0.999}, {"word": "luego", "start": 2.145, "end": 2.648, "score": 0.818}, {"word": "tu", "start": 2.728, "end": 2.869, "score": 0.608}, {"word": "familia", "start": 2.889, "end": 3.231, "score": 0.92}, {"word": "te", "start": 3.332, "end": 3.413, "score": 0.573}, {"word": "obliga", "start": 3.473, "end": 3.775, "score": 0.872}, {"word": "a", "start": 3.795, "end": 3.815, "score": 0.995}, {"word": "casarte", "start": 3.956, "end": 4.339, "score": 0.96}, {"word": "después", "start": 4.399, "end": 4.701, "score": 0.784}, {"word": "de", "start": 4.761, "end": 4.822, "score": 0.964}, {"word": "morir.", "start": 4.882, "end": 5.687, "score": 0.913}]}, {"start": 6.005, "end": 10.509, "text": " En la antigua China, morir soltero significaba enfrentar una eternidad de soledad.", "words": [{"word": "En", "start": 6.005, "end": 6.345, "score": 0.027}, {"word": "la", "start": 6.365, "end": 6.405, "score": 0.268}, {"word": "antigua", "start": 6.425, "end": 6.746, "score": 0.471}, {"word": "China,", "start": 6.846, "end": 7.106, "score": 0.916}, {"word": "morir", "start": 7.506, "end": 7.747, "score": 0.896}, {"word": "soltero", "start": 7.787, "end": 8.187, "score": 0.829}, {"word": "significaba", "start": 8.247, "end": 8.788, "score": 0.909}, {"word": "enfrentar", "start": 8.828, "end": 9.268, "score": 0.699}, {"word": "una", "start": 9.308, "end": 9.448, "score": 0.396}, {"word": "eternidad", "start": 9.508, "end": 9.949, "score": 0.873}, {"word": "de", "start": 10.009, "end": 10.089, "score": 0.92}, {"word": "soledad.", "start": 10.149, "end": 10.509, "score": 0.834}]}, {"start": 11.47, "end": 15.414, "text": "Para solucionar esto, las familias organizaban matrimonios fantasma.", "words": [{"word": "Para", "start": 11.47, "end": 11.59, "score": 0.928}, {"word": "solucionar", "start": 11.69, "end": 12.191, "score": 0.779}, {"word": "esto,", "start": 12.231, "end": 12.551, "score": 0.897}, {"word": "las", "start": 12.932, "end": 13.032, "score": 0.819}, {"word": "familias", "start": 13.112, "end": 13.452, "score": 0.938}, {"word": "organizaban", "start": 13.492, "end": 14.153, "score": 0.783}, {"word": "matrimonios", "start": 14.193, "end": 14.834, "score": 0.896}, {"word": "fantasma.", "start": 14.874, "end": 15.414, "score": 0.766}]}, {"start": 16.495, "end": 29.508, "text": "Literalmente encontraban a dos personas muertas y solteras, vestían efiges de papel de ellos con ropas de boda rojas tradicionales increíblemente vibrantes y realizaban una ceremonia masiva y hermosa antes de enterrarlos uno al lado del otro.", "words": [{"word": "Literalmente", "start": 16.495, "end": 17.096, "score": 0.969}, {"word": "encontraban", "start": 17.136, "end": 17.716, "score": 0.708}, {"word": "a", "start": 17.756, "end": 17.776, "score": 0.201}, {"word": "dos", "start": 17.856, "end": 17.957, "score": 0.942}, {"word": "personas", "start": 18.057, "end": 18.397, "score": 0.88}, {"word": "muertas", "start": 18.437, "end": 18.797, "score": 0.834}, {"word": "y", "start": 18.817, "end": 18.837, "score": 0.996}, {"word": "solteras,", "start": 18.857, "end": 19.418, "score": 0.88}, {"word": "vestían", "start": 19.838, "end": 20.219, "score": 0.944}, {"word": "efiges", "start": 20.279, "end": 20.639, "score": 0.795}, {"word": "de", "start": 20.679, "end": 20.739, "score": 0.64}, {"word": "papel", "start": 20.819, "end": 21.06, "score": 0.921}, {"word": "de", "start": 21.1, "end": 21.18, "score": 0.874}, {"word": "ellos", "start": 21.26, "end": 21.46, "score": 0.883}, {"word": "con", "start": 21.56, "end": 21.66, "score": 0.883}, {"word": "ropas", "start": 21.76, "end": 21.96, "score": 0.937}, {"word": "de", "start": 22.02, "end": 22.06, "score": 0.746}, {"word": "boda", "start": 22.141, "end": 22.321, "score": 0.918}, {"word": "rojas", "start": 22.401, "end": 22.641, "score": 0.792}, {"word": "tradicionales", "start": 22.741, "end": 23.302, "score": 0.835}, {"word": "increíblemente", "start": 23.362, "end": 24.183, "score": 0.89}, {"word": "vibrantes", "start": 24.283, "end": 24.743, "score": 0.968}, {"word": "y", "start": 24.763, "end": 24.783, "score": 0.994}, {"word": "realizaban", "start": 25.284, "end": 25.784, "score": 0.963}, {"word": "una", "start": 25.884, "end": 25.984, "score": 0.89}, {"word": "ceremonia", "start": 26.064, "end": 26.505, "score": 0.803}, {"word": "masiva", "start": 26.605, "end": 26.905, "score": 0.953}, {"word": "y", "start": 26.945, "end": 27.005, "score": 0.356}, {"word": "hermosa", "start": 27.065, "end": 27.426, "score": 0.964}, {"word": "antes", "start": 27.466, "end": 27.746, "score": 0.703}, {"word": "de", "start": 27.786, "end": 27.846, "score": 0.879}, {"word": "enterrarlos", "start": 27.906, "end": 28.447, "score": 0.888}, {"word": "uno", "start": 28.487, "end": 28.687, "score": 0.432}, {"word": "al", "start": 28.747, "end": 28.827, "score": 0.653}, {"word": "lado", "start": 28.887, "end": 29.067, "score": 0.986}, {"word": "del", "start": 29.107, "end": 29.227, "score": 0.818}, {"word": "otro.", "start": 29.287, "end": 29.508, "score": 0.92}]}, {"start": 30.509, "end": 35.033, "text": "Porque el amor verdadero nunca muere solo espera a que tus parientes te emparejen.", "words": [{"word": "Porque", "start": 30.509, "end": 30.769, "score": 0.887}, {"word": "el", "start": 30.829, "end": 30.909, "score": 0.604}, {"word": "amor", "start": 30.949, "end": 31.129, "score": 0.927}, {"word": "verdadero", "start": 31.209, "end": 31.61, "score": 0.912}, {"word": "nunca", "start": 31.65, "end": 31.93, "score": 0.899}, {"word": "muere", "start": 32.01, "end": 32.23, "score": 0.913}, {"word": "solo", "start": 32.27, "end": 32.551, "score": 0.886}, {"word": "espera", "start": 32.591, "end": 32.951, "score": 0.849}, {"word": "a", "start": 32.991, "end": 33.011, "score": 0.308}, {"word": "que", "start": 33.071, "end": 33.151, "score": 0.902}, {"word": "tus", "start": 33.231, "end": 33.371, "score": 0.876}, {"word": "parientes", "start": 33.391, "end": 33.852, "score": 0.811}, {"word": "te", "start": 33.872, "end": 33.972, "score": 0.685}, {"word": "emparejen.", "start": 34.012, "end": 35.033, "score": 0.685}]}, {"start": 35.013, "end": 38.813, "text": " Revisa el enlace de Width History en la descripción para más.", "words": [{"word": "Revisa", "start": 35.013, "end": 35.923, "score": 0.968}, {"word": "el", "start": 35.943, "end": 36.044, "score": 0.577}, {"word": "enlace", "start": 36.105, "end": 36.428, "score": 0.899}, {"word": "de", "start": 36.489, "end": 36.549, "score": 0.92}, {"word": "Width", "start": 36.65, "end": 36.832, "score": 0.555}, {"word": "History", "start": 36.893, "end": 37.338, "score": 0.899}, {"word": "en", "start": 37.418, "end": 37.459, "score": 0.959}, {"word": "la", "start": 37.52, "end": 37.56, "score": 1.0}, {"word": "descripción", "start": 37.621, "end": 38.166, "score": 0.894}, {"word": "para", "start": 38.267, "end": 38.409, "score": 0.926}, {"word": "más.", "start": 38.47, "end": 38.813, "score": 0.954}]}], "word_segments": [{"word": "Imagina", "start": 0.031, "end": 0.695, "score": 0.906}, {"word": "estar", "start": 0.736, "end": 0.957, "score": 0.687}, {"word": "soltero", "start": 0.997, "end": 1.38, "score": 0.835}, {"word": "toda", "start": 1.48, "end": 1.641, "score": 0.783}, {"word": "tu", "start": 1.722, "end": 1.822, "score": 0.734}, {"word": "vida", "start": 1.843, "end": 2.064, "score": 0.978}, {"word": "y", "start": 2.084, "end": 2.104, "score": 0.999}, {"word": "luego", "start": 2.145, "end": 2.648, "score": 0.818}, {"word": "tu", "start": 2.728, "end": 2.869, "score": 0.608}, {"word": "familia", "start": 2.889, "end": 3.231, "score": 0.92}, {"word": "te", "start": 3.332, "end": 3.413, "score": 0.573}, {"word": "obliga", "start": 3.473, "end": 3.775, "score": 0.872}, {"word": "a", "start": 3.795, "end": 3.815, "score": 0.995}, {"word": "casarte", "start": 3.956, "end": 4.339, "score": 0.96}, {"word": "después", "start": 4.399, "end": 4.701, "score": 0.784}, {"word": "de", "start": 4.761, "end": 4.822, "score": 0.964}, {"word": "morir.", "start": 4.882, "end": 5.687, "score": 0.913}, {"word": "En", "start": 6.005, "end": 6.345, "score": 0.027}, {"word": "la", "start": 6.365, "end": 6.405, "score": 0.268}, {"word": "antigua", "start": 6.425, "end": 6.746, "score": 0.471}, {"word": "China,", "start": 6.846, "end": 7.106, "score": 0.916}, {"word": "morir", "start": 7.506, "end": 7.747, "score": 0.896}, {"word": "soltero", "start": 7.787, "end": 8.187, "score": 0.829}, {"word": "significaba", "start": 8.247, "end": 8.788, "score": 0.909}, {"word": "enfrentar", "start": 8.828, "end": 9.268, "score": 0.699}, {"word": "una", "start": 9.308, "end": 9.448, "score": 0.396}, {"word": "eternidad", "start": 9.508, "end": 9.949, "score": 0.873}, {"word": "de", "start": 10.009, "end": 10.089, "score": 0.92}, {"word": "soledad.", "start": 10.149, "end": 10.509, "score": 0.834}, {"word": "Para", "start": 11.47, "end": 11.59, "score": 0.928}, {"word": "solucionar", "start": 11.69, "end": 12.191, "score": 0.779}, {"word": "esto,", "start": 12.231, "end": 12.551, "score": 0.897}, {"word": "las", "start": 12.932, "end": 13.032, "score": 0.819}, {"word": "familias", "start": 13.112, "end": 13.452, "score": 0.938}, {"word": "organizaban", "start": 13.492, "end": 14.153, "score": 0.783}, {"word": "matrimonios", "start": 14.193, "end": 14.834, "score": 0.896}, {"word": "fantasma.", "start": 14.874, "end": 15.414, "score": 0.766}, {"word": "Literalmente", "start": 16.495, "end": 17.096, "score": 0.969}, {"word": "encontraban", "start": 17.136, "end": 17.716, "score": 0.708}, {"word": "a", "start": 17.756, "end": 17.776, "score": 0.201}, {"word": "dos", "start": 17.856, "end": 17.957, "score": 0.942}, {"word": "personas", "start": 18.057, "end": 18.397, "score": 0.88}, {"word": "muertas", "start": 18.437, "end": 18.797, "score": 0.834}, {"word": "y", "start": 18.817, "end": 18.837, "score": 0.996}, {"word": "solteras,", "start": 18.857, "end": 19.418, "score": 0.88}, {"word": "vestían", "start": 19.838, "end": 20.219, "score": 0.944}, {"word": "efiges", "start": 20.279, "end": 20.639, "score": 0.795}, {"word": "de", "start": 20.679, "end": 20.739, "score": 0.64}, {"word": "papel", "start": 20.819, "end": 21.06, "score": 0.921}, {"word": "de", "start": 21.1, "end": 21.18, "score": 0.874}, {"word": "ellos", "start": 21.26, "end": 21.46, "score": 0.883}, {"word": "con", "start": 21.56, "end": 21.66, "score": 0.883}, {"word": "ropas", "start": 21.76, "end": 21.96, "score": 0.937}, {"word": "de", "start": 22.02, "end": 22.06, "score": 0.746}, {"word": "boda", "start": 22.141, "end": 22.321, "score": 0.918}, {"word": "rojas", "start": 22.401, "end": 22.641, "score": 0.792}, {"word": "tradicionales", "start": 22.741, "end": 23.302, "score": 0.835}, {"word": "increíblemente", "start": 23.362, "end": 24.183, "score": 0.89}, {"word": "vibrantes", "start": 24.283, "end": 24.743, "score": 0.968}, {"word": "y", "start": 24.763, "end": 24.783, "score": 0.994}, {"word": "realizaban", "start": 25.284, "end": 25.784, "score": 0.963}, {"word": "una", "start": 25.884, "end": 25.984, "score": 0.89}, {"word": "ceremonia", "start": 26.064, "end": 26.505, "score": 0.803}, {"word": "masiva", "start": 26.605, "end": 26.905, "score": 0.953}, {"word": "y", "start": 26.945, "end": 27.005, "score": 0.356}, {"word": "hermosa", "start": 27.065, "end": 27.426, "score": 0.964}, {"word": "antes", "start": 27.466, "end": 27.746, "score": 0.703}, {"word": "de", "start": 27.786, "end": 27.846, "score": 0.879}, {"word": "enterrarlos", "start": 27.906, "end": 28.447, "score": 0.888}, {"word": "uno", "start": 28.487, "end": 28.687, "score": 0.432}, {"word": "al", "start": 28.747, "end": 28.827, "score": 0.653}, {"word": "lado", "start": 28.887, "end": 29.067, "score": 0.986}, {"word": "del", "start": 29.107, "end": 29.227, "score": 0.818}, {"word": "otro.", "start": 29.287, "end": 29.508, "score": 0.92}, {"word": "Porque", "start": 30.509, "end": 30.769, "score": 0.887}, {"word": "el", "start": 30.829, "end": 30.909, "score": 0.604}, {"word": "amor", "start": 30.949, "end": 31.129, "score": 0.927}, {"word": "verdadero", "start": 31.209, "end": 31.61, "score": 0.912}, {"word": "nunca", "start": 31.65, "end": 31.93, "score": 0.899}, {"word": "muere", "start": 32.01, "end": 32.23, "score": 0.913}, {"word": "solo", "start": 32.27, "end": 32.551, "score": 0.886}, {"word": "espera", "start": 32.591, "end": 32.951, "score": 0.849}, {"word": "a", "start": 32.991, "end": 33.011, "score": 0.308}, {"word": "que", "start": 33.071, "end": 33.151, "score": 0.902}, {"word": "tus", "start": 33.231, "end": 33.371, "score": 0.876}, {"word": "parientes", "start": 33.391, "end": 33.852, "score": 0.811}, {"word": "te", "start": 33.872, "end": 33.972, "score": 0.685}, {"word": "emparejen.", "start": 34.012, "end": 35.033, "score": 0.685}, {"word": "Revisa", "start": 35.013, "end": 35.923, "score": 0.968}, {"word": "el", "start": 35.943, "end": 36.044, "score": 0.577}, {"word": "enlace", "start": 36.105, "end": 36.428, "score": 0.899}, {"word": "de", "start": 36.489, "end": 36.549, "score": 0.92}, {"word": "Width", "start": 36.65, "end": 36.832, "score": 0.555}, {"word": "History", "start": 36.893, "end": 37.338, "score": 0.899}, {"word": "en", "start": 37.418, "end": 37.459, "score": 0.959}, {"word": "la", "start": 37.52, "end": 37.56, "score": 1.0}, {"word": "descripción", "start": 37.621, "end": 38.166, "score": 0.894}, {"word": "para", "start": 38.267, "end": 38.409, "score": 0.926}, {"word": "más.", "start": 38.47, "end": 38.813, "score": 0.954}], "language": "es"}